twhook.py
twhook-0.1.0.dist-info/LICENSE
twhook-0.1.0.dist-info/METADATA
twhook-0.1.0.dist-info/WHEEL
twhook-0.1.0.dist-info/top_level.txt
twhook-0.1.0.dist-info/RECORD
