Metadata-Version: 2.1
Name: twhook
Version: 0.1.0
Summary: Twitter Premium Account Activity API wrapper.
Home-page: https://github.com/nxgeo/twhook
Author: Nikolaus Georgi
License: UNKNOWN
Platform: UNKNOWN
Classifier: Development Status :: 5 - Production/Stable
Classifier: License :: OSI Approved :: MIT License
Requires-Python: >=3.6
License-File: LICENSE
Requires-Dist: requests-oauthlib
